SitanfuCs224dShenduXuexiYuZiranyuyanChuliJiangyi/README.md
SitanfuCs224dShenduXuexiYuZiranyuyanChuliJiangyi/__init__.py
SitanfuCs224dShenduXuexiYuZiranyuyanChuliJiangyi/__main__.py
SitanfuCs224dShenduXuexiYuZiranyuyanChuliJiangyi/file.epub
SitanfuCs224dShenduXuexiYuZiranyuyanChuliJiangyi/index.html
SitanfuCs224dShenduXuexiYuZiranyuyanChuliJiangyi/css/__init__.py
SitanfuCs224dShenduXuexiYuZiranyuyanChuliJiangyi/css/annotations.css
SitanfuCs224dShenduXuexiYuZiranyuyanChuliJiangyi/css/main.css
SitanfuCs224dShenduXuexiYuZiranyuyanChuliJiangyi/css/normalize.css
SitanfuCs224dShenduXuexiYuZiranyuyanChuliJiangyi/css/popup.css
SitanfuCs224dShenduXuexiYuZiranyuyanChuliJiangyi/font/__init__.py
SitanfuCs224dShenduXuexiYuZiranyuyanChuliJiangyi/font/fontello.eot
SitanfuCs224dShenduXuexiYuZiranyuyanChuliJiangyi/font/fontello.svg
SitanfuCs224dShenduXuexiYuZiranyuyanChuliJiangyi/font/fontello.ttf
SitanfuCs224dShenduXuexiYuZiranyuyanChuliJiangyi/font/fontello.woff
SitanfuCs224dShenduXuexiYuZiranyuyanChuliJiangyi/img/__init__.py
SitanfuCs224dShenduXuexiYuZiranyuyanChuliJiangyi/img/annotator-glyph-sprite.png
SitanfuCs224dShenduXuexiYuZiranyuyanChuliJiangyi/img/annotator-icon-sprite.png
SitanfuCs224dShenduXuexiYuZiranyuyanChuliJiangyi/img/apple-touch-icon.png
SitanfuCs224dShenduXuexiYuZiranyuyanChuliJiangyi/img/cancelfullscreen.png
SitanfuCs224dShenduXuexiYuZiranyuyanChuliJiangyi/img/close.png
SitanfuCs224dShenduXuexiYuZiranyuyanChuliJiangyi/img/fullscreen.png
SitanfuCs224dShenduXuexiYuZiranyuyanChuliJiangyi/img/loader.gif
SitanfuCs224dShenduXuexiYuZiranyuyanChuliJiangyi/img/menu-icon.png
SitanfuCs224dShenduXuexiYuZiranyuyanChuliJiangyi/img/save.png
SitanfuCs224dShenduXuexiYuZiranyuyanChuliJiangyi/img/saved.png
SitanfuCs224dShenduXuexiYuZiranyuyanChuliJiangyi/img/settings-s.png
SitanfuCs224dShenduXuexiYuZiranyuyanChuliJiangyi/img/settings.png
SitanfuCs224dShenduXuexiYuZiranyuyanChuliJiangyi/img/star.png
SitanfuCs224dShenduXuexiYuZiranyuyanChuliJiangyi/js/__init__.py
sitanfu_cs224d_shendu_xuexi_yu_ziranyuyan_chuli_jiangyi-2024.3.2.0.dist-info/METADATA
sitanfu_cs224d_shendu_xuexi_yu_ziranyuyan_chuli_jiangyi-2024.3.2.0.dist-info/WHEEL
sitanfu_cs224d_shendu_xuexi_yu_ziranyuyan_chuli_jiangyi-2024.3.2.0.dist-info/entry_points.txt
sitanfu_cs224d_shendu_xuexi_yu_ziranyuyan_chuli_jiangyi-2024.3.2.0.dist-info/top_level.txt
sitanfu_cs224d_shendu_xuexi_yu_ziranyuyan_chuli_jiangyi-2024.3.2.0.dist-info/RECORD
